edrixs/__init__.py
edrixs/_version.py
edrixs/angular_momentum.py
edrixs/basis_transform.py
edrixs/coulomb_utensor.py
edrixs/fedrixs.cpython-36m-x86_64-linux-gnu.so
edrixs/fit_hyb.py
edrixs/fock_basis.py
edrixs/iostream.py
edrixs/manybody_operator.py
edrixs/photon_transition.py
edrixs/plot_spectrum.py
edrixs/rixs_utils.py
edrixs/soc.py
edrixs/solvers.py
edrixs/utils.py
edrixs/wannier_ham.py
edrixs/atom_data/Co.json
edrixs/atom_data/Cr.json
edrixs/atom_data/Cu.json
edrixs/atom_data/Fe.json
edrixs/atom_data/Ir.json
edrixs/atom_data/Mn.json
edrixs/atom_data/Ni.json
edrixs/atom_data/Os.json
edrixs/atom_data/Pu.json
edrixs/atom_data/Re.json
edrixs/atom_data/Sm.json
edrixs/atom_data/Ti.json
edrixs/atom_data/U.json
edrixs/atom_data/V.json
edrixs/tests/__init__.py
edrixs/tests/conftest.py
edrixs/tests/test_examples.py
edrixs/tests/test_utils.py
edrixs-0.0.6.dist-info/DESCRIPTION.rst
edrixs-0.0.6.dist-info/METADATA
edrixs-0.0.6.dist-info/RECORD
edrixs-0.0.6.dist-info/WHEEL
edrixs-0.0.6.dist-info/entry_points.txt
edrixs-0.0.6.dist-info/metadata.json
edrixs-0.0.6.dist-info/top_level.txt
