Metadata-Version: 2.0
Name: edrixs
Version: 0.0.6
Summary: An open source toolkit for simulating RIXS spectra based on ED
Home-page: https://github.com/NSLS-II/edrixs
Author: Brookhaven National Lab
Author-email: yilinwang@bnl.gov
License: BSD (3-clause)
Platform: UNKNOWN
Classifier: Development Status :: 2 - Pre-Alpha
Classifier: Natural Language :: English
Classifier: Programming Language :: Python :: 3
Requires-Dist: matplotlib
Requires-Dist: mpi4py
Requires-Dist: numpy
Requires-Dist: scipy
Requires-Dist: sphinx
Requires-Dist: sympy
